Workbook

Sheet original
A1: Ministry/Department/State | B1: Total Receipts (01.01.2016 to 01.11.2019) | C1: Total Disposal (01.01.2016 to 01.11.2019) | D1: Total Pending as on 01.11.2019 | E1: Pending More Than 1 Year | F1: Pending Between 6 To 12 Months | G1: Pending Between 2 To 6 Months | H1: Pending Less Than 2 Months
A2: Administrative Reforms and PG | B2: 1540 | C2: 1497 | D2: 43 | E2: 0 | F2: 0 | G2: 1 | H2: 42
A3: Agriculture and Cooperation | B3: 21317 | C3: 20557 | D3: 760 | E3: 7 | F3: 21 | G3: 141 | H3: 591
A4: Agriculture Research and Education | B4: 6535 | C4: 6245 | D4: 290 | E4: 0 | F4: 31 | G4: 65 | H4: 194
A5: Animal Husbandry, Dairying | B5: 4835 | C5: 4702 | D5: 133 | E5: 12 | F5: 16 | G5: 28 | H5: 77
A6: Atomic Energy | B6: 5838 | C6: 5279 | D6: 559 | E6: 346 | F6: 73 | G6: 59 | H6: 81
A7: Ayush | B7: 9221 | C7: 9003 | D7: 218 | E7: 0 | F7: 9 | G7: 76 | H7: 133
A8: Bio Technology | B8: 959 | C8: 906 | D8: 53 | E8: 19 | F8: 11 | G8: 10 | H8: 13
A9: Central Board of Direct Taxes (Income Tax) | B9: 140684 | C9: 138030 | D9: 2654 | E9: 0 | F9: 25 | G9: 623 | H9: 2006
A10: Central Board of Excise and Customs | B10: 64611 | C10: 63682 | D10: 929 | E10: 1 | F10: 4 | G10: 66 | H10: 858
A11: Chemicals and Petrochemicals | B11: 2100 | C11: 2083 | D11: 17 | E11: 0 | F11: 1 | G11: 1 | H11: 15
A12: Civil Aviation | B12: 22937 | C12: 22419 | D12: 518 | E12: 6 | F12: 38 | G12: 175 | H12: 299
A13: Coal | B13: 18391 | C13: 17597 | D13: 794 | E13: 139 | F13: 133 | G13: 171 | H13: 351
... A125: West Bengal | B125: 44515 | C125: 1035 | D125: 43480 | E125: 29074 | F125: 5579 | G125: 5625 | H125: 3202
A127: Source | B127: Department of Administrative Reforms and Public Grievances (DARPG), Government of India, OGD Platform India.
B128: Dataset: Department-wise receipts, disposal and pendency of Public Grievance detailed statistics.

Sheet Statistical_Analysis
A1: Ministry/Department/State | B1: Total Receipts (01.01.2016 to 01.11.2019) | C1: Total Disposal (01.01.2016 to 01.11.2019) | D1: Total Pending as on 01.11.2019 | E1: Pending More Than 1 Year | F1: Pending Between 6 To 12 Months | G1: Pending Between 2 To 6 Months | H1: Pending Less Than 2 Months | I1: Disposal Rate (%) | J1: Pending Rate (%)
A2: Administrative Reforms and PG | B2: 1540 | C2: 1497 | D2: 43 | E2: 0 | F2: 0 | G2: 1 | H2: 42 | I2: =IFERROR((C2/B2)*100,0) | J2: =IFERROR((D2/B2)*100,0)
A3: Agriculture and Cooperation | B3: 21317 | C3: 20557 | D3: 760 | E3: 7 | F3: 21 | G3: 141 | H3: 591 | I3: =IFERROR((C3/B3)*100,0) | J3: =IFERROR((D3/B3)*100,0)
A4: Agriculture Research and Education | B4: 6535 | C4: 6245 | D4: 290 | E4: 0 | F4: 31 | G4: 65 | H4: 194 | I4: =IFERROR((C4/B4)*100,0) | J4: =IFERROR((D4/B4)*100,0)
A5: Animal Husbandry, Dairying | B5: 4835 | C5: 4702 | D5: 133 | E5: 12 | F5: 16 | G5: 28 | H5: 77 | I5: =IFERROR((C5/B5)*100,0) | J5: =IFERROR((D5/B5)*100,0)
A6: Atomic Energy | B6: 5838 | C6: 5279 | D6: 559 | E6: 346 | F6: 73 | G6: 59 | H6: 81 | I6: =IFERROR((C6/B6)*100,0) | J6: =IFERROR((D6/B6)*100,0)
A7: Ayush | B7: 9221 | C7: 9003 | D7: 218 | E7: 0 | F7: 9 | G7: 76 | H7: 133 | I7: =IFERROR((C7/B7)*100,0) | J7: =IFERROR((D7/B7)*100,0)
A8: Bio Technology | B8: 959 | C8: 906 | D8: 53 | E8: 19 | F8: 11 | G8: 10 | H8: 13 | I8: =IFERROR((C8/B8)*100,0) | J8: =IFERROR((D8/B8)*100,0)
A9: Central Board of Direct Taxes (Income Tax) | B9: 140684 | C9: 138030 | D9: 2654 | E9: 0 | F9: 25 | G9: 623 | H9: 2006 | I9: =IFERROR((C9/B9)*100,0) | J9: =IFERROR((D9/B9)*100,0)
A10: Central Board of Excise and Customs | B10: 64611 | C10: 63682 | D10: 929 | E10: 1 | F10: 4 | G10: 66 | H10: 858 | I10: =IFERROR((C10/B10)*100,0) | J10: =IFERROR((D10/B10)*100,0)
A11: Chemicals and Petrochemicals | B11: 2100 | C11: 2083 | D11: 17 | E11: 0 | F11: 1 | G11: 1 | H11: 15 | I11: =IFERROR((C11/B11)*100,0) | J11: =IFERROR((D11/B11)*100,0)
A12: Civil Aviation | B12: 22937 | C12: 22419 | D12: 518 | E12: 6 | F12: 38 | G12: 175 | H12: 299 | I12: =IFERROR((C12/B12)*100,0) | J12: =IFERROR((D12/B12)*100,0)
A13: Coal | B13: 18391 | C13: 17597 | D13: 794 | E13: 139 | F13: 133 | G13: 171 | H13: 351 | I13: =IFERROR((C13/B13)*100,0) | J13: =IFERROR((D13/B13)*100,0)
... A125: West Bengal | B125: 44515 | C125: 1035 | D125: 43480 | E125: 29074 | F125: 5579 | G125: 5625 | H125: 3202 | I125: =IFERROR((C125/B125)*100,0) | J125: =IFERROR((D125/B125)*100,0)

Sheet Statistical_Tests
A1: Correlation Analysis
A2: Variable 1 | B2: Variable 2 | C2: Correlation Coefficient (r)
A3: Total Receipts | B3: Total Disposal | C3: =CORREL(Statistical_Analysis!B2:B125,Statistical_Analysis!C2:C125)
A4: Total Receipts | B4: Disposal Rate (%) | C4: =CORREL(Statistical_Analysis!B2:B125,Statistical_Analysis!I2:I125)
A5: Total Disposal | B5: Disposal Rate (%) | C5: =CORREL(Statistical_Analysis!C2:C125,Statistical_Analysis!I2:I125)
A7: Regression Analysis
A8: Independent Variable (X) | B8: Dependent Variable (Y) | C8: R² (R-squared)
A9: Total Receipts | B9: Total Disposal | C9: =RSQ(Statistical_Analysis!C2:C125,Statistical_Analysis!B2:B125)
A11: Regression Slope | B11: =SLOPE(Statistical_Analysis!C2:C125,Statistical_Analysis!B2:B125)
A12: Regression Intercept | B12: =INTERCEPT(Statistical_Analysis!C2:C125,Statistical_Analysis!B2:B125)
